kak_spell/__init__.py
kak_spell/checker.py
kak_spell/cli.py
kak_spell/kak.py
kak_spell-0.3.1.dist-info/entry_points.txt
kak_spell-0.3.1.dist-info/WHEEL
kak_spell-0.3.1.dist-info/METADATA
kak_spell-0.3.1.dist-info/RECORD
