Metadata-Version: 2.1
Name: kak-spell
Version: 0.3.1
Summary: PyEnchant wrapper for Kakoune
Home-page: https://github.com/dmerejkowsky/kak-spell
Author: Dimitri Merejkowsky
Author-email: d.merej@gmail.com
Requires-Python: >=3.6,<4.0
Classifier: Programming Language :: Python :: 3
Classifier: Programming Language :: Python :: 3.6
Classifier: Programming Language :: Python :: 3.7
Classifier: Programming Language :: Python :: 3.8
Classifier: Programming Language :: Python :: 3.9
Requires-Dist: attrs (>=19.3.0,<20.0.0)
Requires-Dist: pyenchant (==3.0.1)
Requires-Dist: pyxdg (>=0.26,<0.27)
